playwright_firefox/__init__.py
playwright_firefox/__main__.py
playwright_firefox/_repo_version.py
playwright_firefox/case_insensitive_dict.py
playwright_firefox/context_managers.py
playwright_firefox/py.typed
playwright_firefox/stealth.py
playwright_firefox/_impl/__init__.py
playwright_firefox/_impl/_accessibility.py
playwright_firefox/_impl/_api_structures.py
playwright_firefox/_impl/_artifact.py
playwright_firefox/_impl/_assertions.py
playwright_firefox/_impl/_async_base.py
playwright_firefox/_impl/_browser.py
playwright_firefox/_impl/_browser_context.py
playwright_firefox/_impl/_browser_type.py
playwright_firefox/_impl/_cdp_session.py
playwright_firefox/_impl/_clock.py
playwright_firefox/_impl/_connection.py
playwright_firefox/_impl/_console_message.py
playwright_firefox/_impl/_dialog.py
playwright_firefox/_impl/_download.py
playwright_firefox/_impl/_driver.py
playwright_firefox/_impl/_element_handle.py
playwright_firefox/_impl/_errors.py
playwright_firefox/_impl/_event_context_manager.py
playwright_firefox/_impl/_fetch.py
playwright_firefox/_impl/_file_chooser.py
playwright_firefox/_impl/_frame.py
playwright_firefox/_impl/_glob.py
playwright_firefox/_impl/_greenlets.py
playwright_firefox/_impl/_har_router.py
playwright_firefox/_impl/_helper.py
playwright_firefox/_impl/_impl_to_api_mapping.py
playwright_firefox/_impl/_input.py
playwright_firefox/_impl/_js_handle.py
playwright_firefox/_impl/_json_pipe.py
playwright_firefox/_impl/_local_utils.py
playwright_firefox/_impl/_locator.py
playwright_firefox/_impl/_map.py
playwright_firefox/_impl/_network.py
playwright_firefox/_impl/_object_factory.py
playwright_firefox/_impl/_page.py
playwright_firefox/_impl/_path_utils.py
playwright_firefox/_impl/_playwright.py
playwright_firefox/_impl/_selectors.py
playwright_firefox/_impl/_set_input_files_helpers.py
playwright_firefox/_impl/_str_utils.py
playwright_firefox/_impl/_stream.py
playwright_firefox/_impl/_sync_base.py
playwright_firefox-1.0.4.dist-info/METADATA
playwright_firefox-1.0.4.dist-info/WHEEL
playwright_firefox-1.0.4.dist-info/entry_points.txt
playwright_firefox-1.0.4.dist-info/top_level.txt
playwright_firefox-1.0.4.dist-info/RECORD
playwright_firefox-1.0.4.dist-info/licenses/LICENSE
